{"is_completed":true,"total_bytes":82308646,"downloaded_bytes":82308646,"title":"springboot_1th整合环境搭建","type_tag":"lua.flv.bili2api.80","cover":"http:\/\/i0.hdslb.com\/bfs\/archive\/4517075da3c49eb89b422ec6988d940106f18bfe.jpg","prefered_video_quality":80,"guessed_total_bytes":0,"total_time_milli":1843423,"danmaku_count":0,"time_update_stamp":1589463678947,"time_create_stamp":1589463530870,"avid":90719678,"spid":0,"seasion_id":0,"page_data":{"cid":154924241,"page":2,"from":"vupload","part":"springboot_2th,使用v-for展示数据","vid":"","has_alias":false,"weblink":"","tid":39,"width":1364,"height":768,"rotate":0}}